kubiki/blocks/__init__.py
kubiki/blocks/conv_block.py
kubiki/blocks/res_block.py
kubiki/datamodules/__init__.py
kubiki/datamodules/base_datamodule.py
kubiki/datamodules/celeba_datamodule.py
kubiki/models/__init__.py
kubiki/models/base_module.py
kubiki/models/cycle_gan/__init__.py
kubiki/models/cycle_gan/components.py
kubiki/models/cycle_gan/cycle_gan_module.py
kubiki/models/wavenet/__init__.py
kubiki/models/wavenet/components.py
kubiki/models/wavenet/wavenet_module.py
kubiki/utils/__init__.py
kubiki/utils/metric_calculator.py
kubiki/utils/parameters_counter.py
kubiki/utils/randomizer.py
kubiki-0.0.2.dist-info/LICENSE
kubiki-0.0.2.dist-info/METADATA
kubiki-0.0.2.dist-info/WHEEL
kubiki-0.0.2.dist-info/top_level.txt
kubiki-0.0.2.dist-info/RECORD
